meta_tools/__init__.py
meta_tools/__main__.py
meta_tools/py.typed
meta_tools/encodings/reify-defined.lp
meta_tools/encodings/show_unhidden.lp
meta_tools/encodings/viz.lp
meta_tools/extensions/__init__.py
meta_tools/extensions/base_extension.py
meta_tools/extensions/show/encoding.lp
meta_tools/extensions/show/show_extension.py
meta_tools/extensions/tag/encoding.lp
meta_tools/extensions/tag/tag_extension.py
meta_tools/utils/__init__.py
meta_tools/utils/logging.py
meta_tools/utils/parser.py
meta_tools/utils/theory.py
meta_tools/utils/visualization.py
meta_tools_clingo-0.3.6.dist-info/licenses/LICENSE
meta_tools_clingo-0.3.6.dist-info/METADATA
meta_tools_clingo-0.3.6.dist-info/WHEEL
meta_tools_clingo-0.3.6.dist-info/entry_points.txt
meta_tools_clingo-0.3.6.dist-info/top_level.txt
meta_tools_clingo-0.3.6.dist-info/RECORD
