Metadata-Version: 2.4
Name: meta-tools-clingo
Version: 0.3.6
Summary: A template project.
Author-email: Susana Hahn <hahnmartinlu@uni-potsdam.de>
License: MIT License
Project-URL: Homepage, https://github.com/krr-up/meta-tools.git/
Requires-Python: >=3.10
License-File: LICENSE
Requires-Dist: clingo>=5.6.0
Requires-Dist: rich-argparse
Requires-Dist: clingox
Requires-Dist: clingraph
Provides-Extra: format
Requires-Dist: black; extra == "format"
Requires-Dist: isort; extra == "format"
Requires-Dist: autoflake; extra == "format"
Provides-Extra: lint-pylint
Requires-Dist: pylint; extra == "lint-pylint"
Provides-Extra: typecheck
Requires-Dist: types-setuptools; extra == "typecheck"
Requires-Dist: mypy; extra == "typecheck"
Provides-Extra: test
Requires-Dist: coverage[toml]; extra == "test"
Provides-Extra: doc
Requires-Dist: mkdocs; extra == "doc"
Requires-Dist: mkdocs-material; extra == "doc"
Requires-Dist: mkdocstrings[python]; extra == "doc"
Requires-Dist: mkdoclingo; extra == "doc"
Provides-Extra: dev
Requires-Dist: meta-tools-clingo[lint_pylint,test,typecheck]; extra == "dev"
Dynamic: license-file
